{
  "$schema": "https://raw.githubusercontent.com/dineug/erd-editor/main/json-schema/schema.json",
  "version": "3.0.0",
  "settings": {
    "width": 2000,
    "height": 2000,
    "scrollTop": -508.0001,
    "scrollLeft": -29.0655,
    "zoomLevel": 0.88,
    "show": 431,
    "database": 4,
    "databaseName": "",
    "canvasType": "ERD",
    "language": 1,
    "tableNameCase": 4,
    "columnNameCase": 2,
    "bracketType": 1,
    "relationshipDataTypeSync": true,
    "relationshipOptimization": false,
    "columnOrder": [
      1,
      2,
      4,
      8,
      16,
      32,
      64
    ],
    "maxWidthComment": -1,
    "ignoreSaveSettings": 0
  },
  "doc": {
    "tableIds": [
      "6NLjero_CG8SoccE9rdSb",
      "O_KZt4w_GaEXBxm1q6T4N",
      "s7eItK9H7Df7CxfMMAvVc",
      "8ihbOgoJ8u9pei3PAiJQp"
    ],
    "relationshipIds": [],
    "indexIds": [],
    "memoIds": []
  },
  "collections": {
    "tableEntities": {
      "6NLjero_CG8SoccE9rdSb": {
        "id": "6NLjero_CG8SoccE9rdSb",
        "name": "Home Banner",
        "comment": "",
        "columnIds": [
          "gMoGlZcUy2nZ7iJ7gykDP",
          "YW9PRZJB1iW0SffSKERz2",
          "M3kXsRJdT-qLvXqIZ0OVM",
          "9ayn4q6dZSGyx3rbhuw4G",
          "ZMWP6VwF4kgkZAYy9L6Hp",
          "UIv5U3DP8ubyOfdZbBouQ",
          "MM53Yu4yqgKY0Jjp3P8dH"
        ],
        "seqColumnIds": [
          "gMoGlZcUy2nZ7iJ7gykDP",
          "YW9PRZJB1iW0SffSKERz2",
          "M3kXsRJdT-qLvXqIZ0OVM",
          "9ayn4q6dZSGyx3rbhuw4G",
          "ZMWP6VwF4kgkZAYy9L6Hp",
          "UIv5U3DP8ubyOfdZbBouQ",
          "MM53Yu4yqgKY0Jjp3P8dH"
        ],
        "ui": {
          "x": 102,
          "y": 91,
          "zIndex": 2,
          "widthName": 74,
          "widthComment": 60,
          "color": ""
        },
        "meta": {
          "updateAt": 1740818765254,
          "createAt": 1740817367345
        }
      },
      "O_KZt4w_GaEXBxm1q6T4N": {
        "id": "O_KZt4w_GaEXBxm1q6T4N",
        "name": "Speaker",
        "comment": "",
        "columnIds": [
          "9r4WzV3p1hxOHlu9y8UDi",
          "XA2J6F1Api_0R2TkLfOQ4",
          "zVNX2OC_BkTLN305DExuO",
          "1XHKhN1CMANpdZUDrCRS8",
          "4qesj4XTKgDNXODMYDHUo",
          "6TkrQSkiMfL2QuwIsdBkj",
          "7JnLizTpvp6JGNTH_Y8E1",
          "h2vZUSFpRlEmiRnm_joY0",
          "_Ni_qUkjq4gYDDqTTiQOQ",
          "Tcq46_L8xwAXd9flInDdD",
          "NEsmgxsnXTmk6jEy_6S4k",
          "Oew1_FnzbVAFTngwh6kSj",
          "ufdTWdWyukUty_npLeSmD",
          "DQtL8os_EbRBQu-IFQek0"
        ],
        "seqColumnIds": [
          "9r4WzV3p1hxOHlu9y8UDi",
          "XA2J6F1Api_0R2TkLfOQ4",
          "zVNX2OC_BkTLN305DExuO",
          "1XHKhN1CMANpdZUDrCRS8",
          "4qesj4XTKgDNXODMYDHUo",
          "6TkrQSkiMfL2QuwIsdBkj",
          "7JnLizTpvp6JGNTH_Y8E1",
          "h2vZUSFpRlEmiRnm_joY0",
          "_Ni_qUkjq4gYDDqTTiQOQ",
          "Tcq46_L8xwAXd9flInDdD",
          "NEsmgxsnXTmk6jEy_6S4k",
          "Oew1_FnzbVAFTngwh6kSj",
          "ufdTWdWyukUty_npLeSmD",
          "DQtL8os_EbRBQu-IFQek0"
        ],
        "ui": {
          "x": 585,
          "y": 82,
          "zIndex": 3,
          "widthName": 60,
          "widthComment": 60,
          "color": ""
        },
        "meta": {
          "updateAt": 1741052489887,
          "createAt": 1740979057805
        }
      },
      "s7eItK9H7Df7CxfMMAvVc": {
        "id": "s7eItK9H7Df7CxfMMAvVc",
        "name": "ScheduleDay",
        "comment": "",
        "columnIds": [
          "peNOzJsgbW_2BlyIOv2iu",
          "rhDv1LegezxnY7ChPCpeP",
          "VMNzb79aawyDsz9A4gtAp",
          "Ci8eopPAGGb6A_qn20nsB"
        ],
        "seqColumnIds": [
          "peNOzJsgbW_2BlyIOv2iu",
          "rhDv1LegezxnY7ChPCpeP",
          "VMNzb79aawyDsz9A4gtAp",
          "Ci8eopPAGGb6A_qn20nsB"
        ],
        "ui": {
          "x": 112.5744,
          "y": 399.2423,
          "zIndex": 4,
          "widthName": 70,
          "widthComment": 60,
          "color": ""
        },
        "meta": {
          "updateAt": 1741488741711,
          "createAt": 1741488674420
        }
      },
      "8ihbOgoJ8u9pei3PAiJQp": {
        "id": "8ihbOgoJ8u9pei3PAiJQp",
        "name": "SponsorsCategories",
        "comment": "",
        "columnIds": [
          "H22qQBeHqZrsNv_8aMTJN",
          "aBobkVX-IEz8gHg_lOXnm",
          "Z0COyh-4DexBCRe73dcfO",
          "iPhncBLgaOTCzZ5AK6sww"
        ],
        "seqColumnIds": [
          "H22qQBeHqZrsNv_8aMTJN",
          "aBobkVX-IEz8gHg_lOXnm",
          "Z0COyh-4DexBCRe73dcfO",
          "iPhncBLgaOTCzZ5AK6sww"
        ],
        "ui": {
          "x": 210.3017,
          "y": 838.6363,
          "zIndex": 5,
          "widthName": 107,
          "widthComment": 60,
          "color": ""
        },
        "meta": {
          "updateAt": 1741662818632,
          "createAt": 1741662274334
        }
      }
    },
    "tableColumnEntities": {
      "gMoGlZcUy2nZ7iJ7gykDP": {
        "id": "gMoGlZcUy2nZ7iJ7gykDP",
        "tableId": "6NLjero_CG8SoccE9rdSb",
        "name": "id",
        "comment": "",
        "dataType": "INT",
        "default": "",
        "options": 10,
        "ui": {
          "keys": 1,
          "widthName": 60,
          "widthComment": 60,
          "widthDataType": 60,
          "widthDefault": 60
        },
        "meta": {
          "updateAt": 1740817498118,
          "createAt": 1740817386439
        }
      },
      "YW9PRZJB1iW0SffSKERz2": {
        "id": "YW9PRZJB1iW0SffSKERz2",
        "tableId": "6NLjero_CG8SoccE9rdSb",
        "name": "heading",
        "comment": "",
        "dataType": "VARCHAR",
        "default": "",
        "options": 8,
        "ui": {
          "keys": 0,
          "widthName": 60,
          "widthComment": 60,
          "widthDataType": 60,
          "widthDefault": 60
        },
        "meta": {
          "updateAt": 1740817518221,
          "createAt": 1740817499597
        }
      },
      "M3kXsRJdT-qLvXqIZ0OVM": {
        "id": "M3kXsRJdT-qLvXqIZ0OVM",
        "tableId": "6NLjero_CG8SoccE9rdSb",
        "name": "subheading",
        "comment": "",
        "dataType": "VARCHAR",
        "default": "",
        "options": 8,
        "ui": {
          "keys": 0,
          "widthName": 64,
          "widthComment": 60,
          "widthDataType": 60,
          "widthDefault": 60
        },
        "meta": {
          "updateAt": 1740817530161,
          "createAt": 1740817521417
        }
      },
      "9ayn4q6dZSGyx3rbhuw4G": {
        "id": "9ayn4q6dZSGyx3rbhuw4G",
        "tableId": "6NLjero_CG8SoccE9rdSb",
        "name": "text",
        "comment": "",
        "dataType": "TEXT",
        "default": "",
        "options": 0,
        "ui": {
          "keys": 0,
          "widthName": 60,
          "widthComment": 60,
          "widthDataType": 60,
          "widthDefault": 60
        },
        "meta": {
          "updateAt": 1740817550715,
          "createAt": 1740817531370
        }
      },
      "ZMWP6VwF4kgkZAYy9L6Hp": {
        "id": "ZMWP6VwF4kgkZAYy9L6Hp",
        "tableId": "6NLjero_CG8SoccE9rdSb",
        "name": "background",
        "comment": "",
        "dataType": "VARCHAR",
        "default": "",
        "options": 8,
        "ui": {
          "keys": 0,
          "widthName": 66,
          "widthComment": 60,
          "widthDataType": 60,
          "widthDefault": 60
        },
        "meta": {
          "updateAt": 1740817574350,
          "createAt": 1740817556842
        }
      },
      "UIv5U3DP8ubyOfdZbBouQ": {
        "id": "UIv5U3DP8ubyOfdZbBouQ",
        "tableId": "6NLjero_CG8SoccE9rdSb",
        "name": "event_date",
        "comment": "",
        "dataType": "VARCHAR",
        "default": "",
        "options": 8,
        "ui": {
          "keys": 0,
          "widthName": 60,
          "widthComment": 60,
          "widthDataType": 60,
          "widthDefault": 60
        },
        "meta": {
          "updateAt": 1740818622802,
          "createAt": 1740818614411
        }
      },
      "MM53Yu4yqgKY0Jjp3P8dH": {
        "id": "MM53Yu4yqgKY0Jjp3P8dH",
        "tableId": "6NLjero_CG8SoccE9rdSb",
        "name": "event_time",
        "comment": "",
        "dataType": "VARCHAR",
        "default": "",
        "options": 8,
        "ui": {
          "keys": 0,
          "widthName": 60,
          "widthComment": 60,
          "widthDataType": 60,
          "widthDefault": 60
        },
        "meta": {
          "updateAt": 1740818633066,
          "createAt": 1740818624322
        }
      },
      "XA2J6F1Api_0R2TkLfOQ4": {
        "id": "XA2J6F1Api_0R2TkLfOQ4",
        "tableId": "O_KZt4w_GaEXBxm1q6T4N",
        "name": "name",
        "comment": "",
        "dataType": "VARCHAR",
        "default": "",
        "options": 8,
        "ui": {
          "keys": 0,
          "widthName": 60,
          "widthComment": 60,
          "widthDataType": 60,
          "widthDefault": 60
        },
        "meta": {
          "updateAt": 1740979723352,
          "createAt": 1740979712444
        }
      },
      "9r4WzV3p1hxOHlu9y8UDi": {
        "id": "9r4WzV3p1hxOHlu9y8UDi",
        "tableId": "O_KZt4w_GaEXBxm1q6T4N",
        "name": "id",
        "comment": "",
        "dataType": "INT",
        "default": "",
        "options": 10,
        "ui": {
          "keys": 1,
          "widthName": 60,
          "widthComment": 60,
          "widthDataType": 60,
          "widthDefault": 60
        },
        "meta": {
          "updateAt": 1740979738908,
          "createAt": 1740979728979
        }
      },
      "1XHKhN1CMANpdZUDrCRS8": {
        "id": "1XHKhN1CMANpdZUDrCRS8",
        "tableId": "O_KZt4w_GaEXBxm1q6T4N",
        "name": "designation",
        "comment": "",
        "dataType": "VARCHAR",
        "default": "",
        "options": 8,
        "ui": {
          "keys": 0,
          "widthName": 64,
          "widthComment": 60,
          "widthDataType": 60,
          "widthDefault": 60
        },
        "meta": {
          "updateAt": 1740979750977,
          "createAt": 1740979742386
        }
      },
      "4qesj4XTKgDNXODMYDHUo": {
        "id": "4qesj4XTKgDNXODMYDHUo",
        "tableId": "O_KZt4w_GaEXBxm1q6T4N",
        "name": "photo",
        "comment": "",
        "dataType": "VARCHAR",
        "default": "",
        "options": 8,
        "ui": {
          "keys": 0,
          "widthName": 60,
          "widthComment": 60,
          "widthDataType": 60,
          "widthDefault": 60
        },
        "meta": {
          "updateAt": 1740979759697,
          "createAt": 1740979753700
        }
      },
      "6TkrQSkiMfL2QuwIsdBkj": {
        "id": "6TkrQSkiMfL2QuwIsdBkj",
        "tableId": "O_KZt4w_GaEXBxm1q6T4N",
        "name": "email",
        "comment": "",
        "dataType": "VARCHAR",
        "default": "",
        "options": 8,
        "ui": {
          "keys": 0,
          "widthName": 60,
          "widthComment": 60,
          "widthDataType": 60,
          "widthDefault": 60
        },
        "meta": {
          "updateAt": 1740979768385,
          "createAt": 1740979761095
        }
      },
      "7JnLizTpvp6JGNTH_Y8E1": {
        "id": "7JnLizTpvp6JGNTH_Y8E1",
        "tableId": "O_KZt4w_GaEXBxm1q6T4N",
        "name": "phone",
        "comment": "",
        "dataType": "VARCHAR",
        "default": "",
        "options": 8,
        "ui": {
          "keys": 0,
          "widthName": 60,
          "widthComment": 60,
          "widthDataType": 60,
          "widthDefault": 60
        },
        "meta": {
          "updateAt": 1740979775746,
          "createAt": 1740979769741
        }
      },
      "h2vZUSFpRlEmiRnm_joY0": {
        "id": "h2vZUSFpRlEmiRnm_joY0",
        "tableId": "O_KZt4w_GaEXBxm1q6T4N",
        "name": "biography",
        "comment": "",
        "dataType": "TEXT",
        "default": "",
        "options": 0,
        "ui": {
          "keys": 0,
          "widthName": 60,
          "widthComment": 60,
          "widthDataType": 60,
          "widthDefault": 60
        },
        "meta": {
          "updateAt": 1740979782415,
          "createAt": 1740979777045
        }
      },
      "_Ni_qUkjq4gYDDqTTiQOQ": {
        "id": "_Ni_qUkjq4gYDDqTTiQOQ",
        "tableId": "O_KZt4w_GaEXBxm1q6T4N",
        "name": "address",
        "comment": "",
        "dataType": "VARCHAR",
        "default": "",
        "options": 0,
        "ui": {
          "keys": 0,
          "widthName": 60,
          "widthComment": 60,
          "widthDataType": 60,
          "widthDefault": 60
        },
        "meta": {
          "updateAt": 1740979818923,
          "createAt": 1740979789403
        }
      },
      "Tcq46_L8xwAXd9flInDdD": {
        "id": "Tcq46_L8xwAXd9flInDdD",
        "tableId": "O_KZt4w_GaEXBxm1q6T4N",
        "name": "website",
        "comment": "",
        "dataType": "VARCHAR",
        "default": "",
        "options": 0,
        "ui": {
          "keys": 0,
          "widthName": 60,
          "widthComment": 60,
          "widthDataType": 60,
          "widthDefault": 60
        },
        "meta": {
          "updateAt": 1740979812674,
          "createAt": 1740979804357
        }
      },
      "NEsmgxsnXTmk6jEy_6S4k": {
        "id": "NEsmgxsnXTmk6jEy_6S4k",
        "tableId": "O_KZt4w_GaEXBxm1q6T4N",
        "name": "facebook",
        "comment": "",
        "dataType": "VARCHAR",
        "default": "",
        "options": 0,
        "ui": {
          "keys": 0,
          "widthName": 60,
          "widthComment": 60,
          "widthDataType": 60,
          "widthDefault": 60
        },
        "meta": {
          "updateAt": 1740979829211,
          "createAt": 1740979821635
        }
      },
      "Oew1_FnzbVAFTngwh6kSj": {
        "id": "Oew1_FnzbVAFTngwh6kSj",
        "tableId": "O_KZt4w_GaEXBxm1q6T4N",
        "name": "twitter",
        "comment": "",
        "dataType": "VARCHAR",
        "default": "",
        "options": 0,
        "ui": {
          "keys": 0,
          "widthName": 60,
          "widthComment": 60,
          "widthDataType": 60,
          "widthDefault": 60
        },
        "meta": {
          "updateAt": 1740979837437,
          "createAt": 1740979830717
        }
      },
      "ufdTWdWyukUty_npLeSmD": {
        "id": "ufdTWdWyukUty_npLeSmD",
        "tableId": "O_KZt4w_GaEXBxm1q6T4N",
        "name": "linkedin",
        "comment": "",
        "dataType": "VARCHAR",
        "default": "",
        "options": 0,
        "ui": {
          "keys": 0,
          "widthName": 60,
          "widthComment": 60,
          "widthDataType": 60,
          "widthDefault": 60
        },
        "meta": {
          "updateAt": 1740979843738,
          "createAt": 1740979838871
        }
      },
      "DQtL8os_EbRBQu-IFQek0": {
        "id": "DQtL8os_EbRBQu-IFQek0",
        "tableId": "O_KZt4w_GaEXBxm1q6T4N",
        "name": "instagram",
        "comment": "",
        "dataType": "VARCHAR",
        "default": "",
        "options": 0,
        "ui": {
          "keys": 0,
          "widthName": 60,
          "widthComment": 60,
          "widthDataType": 60,
          "widthDefault": 60
        },
        "meta": {
          "updateAt": 1740979854061,
          "createAt": 1740979845319
        }
      },
      "zVNX2OC_BkTLN305DExuO": {
        "id": "zVNX2OC_BkTLN305DExuO",
        "tableId": "O_KZt4w_GaEXBxm1q6T4N",
        "name": "slug",
        "comment": "",
        "dataType": "VARCHAR",
        "default": "",
        "options": 0,
        "ui": {
          "keys": 0,
          "widthName": 60,
          "widthComment": 60,
          "widthDataType": 60,
          "widthDefault": 60
        },
        "meta": {
          "updateAt": 1741052495783,
          "createAt": 1741052487864
        }
      },
      "peNOzJsgbW_2BlyIOv2iu": {
        "id": "peNOzJsgbW_2BlyIOv2iu",
        "tableId": "s7eItK9H7Df7CxfMMAvVc",
        "name": "id",
        "comment": "",
        "dataType": "INT",
        "default": "",
        "options": 8,
        "ui": {
          "keys": 0,
          "widthName": 60,
          "widthComment": 60,
          "widthDataType": 60,
          "widthDefault": 60
        },
        "meta": {
          "updateAt": 1741488706939,
          "createAt": 1741488697644
        }
      },
      "rhDv1LegezxnY7ChPCpeP": {
        "id": "rhDv1LegezxnY7ChPCpeP",
        "tableId": "s7eItK9H7Df7CxfMMAvVc",
        "name": "day",
        "comment": "",
        "dataType": "VARCHAR",
        "default": "",
        "options": 8,
        "ui": {
          "keys": 0,
          "widthName": 60,
          "widthComment": 60,
          "widthDataType": 60,
          "widthDefault": 60
        },
        "meta": {
          "updateAt": 1741488722107,
          "createAt": 1741488708683
        }
      },
      "VMNzb79aawyDsz9A4gtAp": {
        "id": "VMNzb79aawyDsz9A4gtAp",
        "tableId": "s7eItK9H7Df7CxfMMAvVc",
        "name": "date1",
        "comment": "",
        "dataType": "VARCHAR",
        "default": "",
        "options": 8,
        "ui": {
          "keys": 0,
          "widthName": 60,
          "widthComment": 60,
          "widthDataType": 60,
          "widthDefault": 60
        },
        "meta": {
          "updateAt": 1741488731555,
          "createAt": 1741488723211
        }
      },
      "Ci8eopPAGGb6A_qn20nsB": {
        "id": "Ci8eopPAGGb6A_qn20nsB",
        "tableId": "s7eItK9H7Df7CxfMMAvVc",
        "name": "order1",
        "comment": "",
        "dataType": "VARCHAR",
        "default": "",
        "options": 8,
        "ui": {
          "keys": 0,
          "widthName": 60,
          "widthComment": 60,
          "widthDataType": 60,
          "widthDefault": 60
        },
        "meta": {
          "updateAt": 1741488739986,
          "createAt": 1741488732867
        }
      },
      "H22qQBeHqZrsNv_8aMTJN": {
        "id": "H22qQBeHqZrsNv_8aMTJN",
        "tableId": "8ihbOgoJ8u9pei3PAiJQp",
        "name": "id",
        "comment": "",
        "dataType": "INT",
        "default": "",
        "options": 8,
        "ui": {
          "keys": 0,
          "widthName": 60,
          "widthComment": 60,
          "widthDataType": 60,
          "widthDefault": 60
        },
        "meta": {
          "updateAt": 1741662717417,
          "createAt": 1741662708593
        }
      },
      "aBobkVX-IEz8gHg_lOXnm": {
        "id": "aBobkVX-IEz8gHg_lOXnm",
        "tableId": "8ihbOgoJ8u9pei3PAiJQp",
        "name": "name",
        "comment": "",
        "dataType": "VARCHAR",
        "default": "",
        "options": 8,
        "ui": {
          "keys": 0,
          "widthName": 60,
          "widthComment": 60,
          "widthDataType": 60,
          "widthDefault": 60
        },
        "meta": {
          "updateAt": 1741662802561,
          "createAt": 1741662718712
        }
      },
      "Z0COyh-4DexBCRe73dcfO": {
        "id": "Z0COyh-4DexBCRe73dcfO",
        "tableId": "8ihbOgoJ8u9pei3PAiJQp",
        "name": "description",
        "comment": "",
        "dataType": "TEXT",
        "default": "",
        "options": 0,
        "ui": {
          "keys": 0,
          "widthName": 61,
          "widthComment": 60,
          "widthDataType": 60,
          "widthDefault": 60
        },
        "meta": {
          "updateAt": 1741662817352,
          "createAt": 1741662803475
        }
      },
      "iPhncBLgaOTCzZ5AK6sww": {
        "id": "iPhncBLgaOTCzZ5AK6sww",
        "tableId": "8ihbOgoJ8u9pei3PAiJQp",
        "name": "",
        "comment": "",
        "dataType": "",
        "default": "",
        "options": 0,
        "ui": {
          "keys": 0,
          "widthName": 60,
          "widthComment": 60,
          "widthDataType": 60,
          "widthDefault": 60
        },
        "meta": {
          "updateAt": 1741662818632,
          "createAt": 1741662818632
        }
      }
    },
    "relationshipEntities": {},
    "indexEntities": {},
    "indexColumnEntities": {},
    "memoEntities": {}
  },
  "lww": {
    "6NLjero_CG8SoccE9rdSb": [
      "tableEntities",
      1740817367340,
      -1,
      {
        "name": 1740817595745
      }
    ],
    "gMoGlZcUy2nZ7iJ7gykDP": [
      "tableColumnEntities",
      1740817386436,
      -1,
      {
        "name": 1740817487785,
        "dataType": 1740817491340,
        "options(notNull)": 1740817492292,
        "options(primaryKey)": 1740817498116
      }
    ],
    "YW9PRZJB1iW0SffSKERz2": [
      "tableColumnEntities",
      1740817499596,
      -1,
      {
        "name": 1740817507253,
        "dataType": 1740817517308,
        "options(notNull)": 1740817518220
      }
    ],
    "M3kXsRJdT-qLvXqIZ0OVM": [
      "tableColumnEntities",
      1740817521417,
      -1,
      {
        "name": 1740817526733,
        "dataType": 1740817529185,
        "options(notNull)": 1740817530161
      }
    ],
    "9ayn4q6dZSGyx3rbhuw4G": [
      "tableColumnEntities",
      1740817531369,
      -1,
      {
        "name": 1740817544669,
        "dataType": 1740817550713
      }
    ],
    "ZMWP6VwF4kgkZAYy9L6Hp": [
      "tableColumnEntities",
      1740817556841,
      -1,
      {
        "name": 1740817574347,
        "dataType": 1740817562025,
        "options(notNull)": 1740817563739
      }
    ],
    "UIv5U3DP8ubyOfdZbBouQ": [
      "tableColumnEntities",
      1740818614409,
      -1,
      {
        "name": 1740818618907,
        "dataType": 1740818621785,
        "options(notNull)": 1740818622801
      }
    ],
    "MM53Yu4yqgKY0Jjp3P8dH": [
      "tableColumnEntities",
      1740818624321,
      -1,
      {
        "name": 1740818629223,
        "dataType": 1740818631889,
        "options(notNull)": 1740818633065
      }
    ],
    "O_KZt4w_GaEXBxm1q6T4N": [
      "tableEntities",
      1740979057801,
      -1,
      {
        "name": 1740979063533
      }
    ],
    "XA2J6F1Api_0R2TkLfOQ4": [
      "tableColumnEntities",
      1740979712435,
      -1,
      {
        "name": 1740979717508,
        "dataType": 1740979721454,
        "options(notNull)": 1740979723343
      }
    ],
    "9r4WzV3p1hxOHlu9y8UDi": [
      "tableColumnEntities",
      1740979728958,
      -1,
      {
        "name": 1740979731091,
        "dataType": 1740979735358,
        "options(notNull)": 1740979736062,
        "options(primaryKey)": 1740979738902
      }
    ],
    "1XHKhN1CMANpdZUDrCRS8": [
      "tableColumnEntities",
      1740979742374,
      -1,
      {
        "name": 1740979747210,
        "dataType": 1740979750038,
        "options(notNull)": 1740979750974
      }
    ],
    "4qesj4XTKgDNXODMYDHUo": [
      "tableColumnEntities",
      1740979753686,
      -1,
      {
        "name": 1740979757128,
        "dataType": 1740979759022,
        "options(notNull)": 1740979759694
      }
    ],
    "6TkrQSkiMfL2QuwIsdBkj": [
      "tableColumnEntities",
      1740979761078,
      -1,
      {
        "name": 1740979765757,
        "dataType": 1740979767726,
        "options(notNull)": 1740979768382
      }
    ],
    "7JnLizTpvp6JGNTH_Y8E1": [
      "tableColumnEntities",
      1740979769726,
      -1,
      {
        "name": 1740979773060,
        "dataType": 1740979774974,
        "options(notNull)": 1740979775742
      }
    ],
    "h2vZUSFpRlEmiRnm_joY0": [
      "tableColumnEntities",
      1740979777030,
      -1,
      {
        "name": 1740979780397,
        "dataType": 1740979782406
      }
    ],
    "_Ni_qUkjq4gYDDqTTiQOQ": [
      "tableColumnEntities",
      1740979789390,
      -1,
      {
        "name": 1740979794914,
        "dataType": 1740979802486,
        "options(notNull)": 1740979818918
      }
    ],
    "Tcq46_L8xwAXd9flInDdD": [
      "tableColumnEntities",
      1740979804342,
      -1,
      {
        "name": 1740979807442,
        "dataType": 1740979809206,
        "options(notNull)": 1740979812670
      }
    ],
    "NEsmgxsnXTmk6jEy_6S4k": [
      "tableColumnEntities",
      1740979821622,
      -1,
      {
        "name": 1740979826688,
        "dataType": 1740979829198
      }
    ],
    "Oew1_FnzbVAFTngwh6kSj": [
      "tableColumnEntities",
      1740979830710,
      -1,
      {
        "name": 1740979833912,
        "dataType": 1740979837430
      }
    ],
    "ufdTWdWyukUty_npLeSmD": [
      "tableColumnEntities",
      1740979838862,
      -1,
      {
        "name": 1740979841522,
        "dataType": 1740979843734
      }
    ],
    "DQtL8os_EbRBQu-IFQek0": [
      "tableColumnEntities",
      1740979845310,
      -1,
      {
        "name": 1740979848020,
        "dataType": 1740979854047
      }
    ],
    "zVNX2OC_BkTLN305DExuO": [
      "tableColumnEntities",
      1741052487859,
      -1,
      {
        "name": 1741052492408,
        "dataType": 1741052495782
      }
    ],
    "s7eItK9H7Df7CxfMMAvVc": [
      "tableEntities",
      1741488674419,
      -1,
      {
        "name": 1741488694927
      }
    ],
    "peNOzJsgbW_2BlyIOv2iu": [
      "tableColumnEntities",
      1741488697642,
      -1,
      {
        "name": 1741488700649,
        "dataType": 1741488705890,
        "options(notNull)": 1741488706938
      }
    ],
    "rhDv1LegezxnY7ChPCpeP": [
      "tableColumnEntities",
      1741488708682,
      -1,
      {
        "name": 1741488712847,
        "dataType": 1741488721322,
        "options(notNull)": 1741488722106
      }
    ],
    "VMNzb79aawyDsz9A4gtAp": [
      "tableColumnEntities",
      1741488723210,
      -1,
      {
        "name": 1741488726478,
        "dataType": 1741488730410,
        "options(notNull)": 1741488731554
      }
    ],
    "Ci8eopPAGGb6A_qn20nsB": [
      "tableColumnEntities",
      1741488732866,
      -1,
      {
        "name": 1741488736532,
        "dataType": 1741488738954,
        "options(notNull)": 1741488739986
      }
    ],
    "8ihbOgoJ8u9pei3PAiJQp": [
      "tableEntities",
      1741662274331,
      -1,
      {
        "name": 1741662783323
      }
    ],
    "H22qQBeHqZrsNv_8aMTJN": [
      "tableColumnEntities",
      1741662708592,
      -1,
      {
        "name": 1741662710837,
        "dataType": 1741662716720,
        "options(notNull)": 1741662717416
      }
    ],
    "aBobkVX-IEz8gHg_lOXnm": [
      "tableColumnEntities",
      1741662718711,
      -1,
      {
        "name": 1741662797601,
        "dataType": 1741662801536,
        "options(notNull)": 1741662802559
      }
    ],
    "Z0COyh-4DexBCRe73dcfO": [
      "tableColumnEntities",
      1741662803472,
      -1,
      {
        "name": 1741662809065,
        "dataType": 1741662812295,
        "options(notNull)": 1741662817351
      }
    ],
    "iPhncBLgaOTCzZ5AK6sww": [
      "tableColumnEntities",
      1741662818631,
      -1,
      {}
    ]
  }
}